bajes/__init__.py
bajes/__main__.py
bajes/inf/__init__.py
bajes/inf/likelihood.py
bajes/inf/prior.py
bajes/inf/utils.py
bajes/inf/sampler/__init__.py
bajes/inf/sampler/cpnest.py
bajes/inf/sampler/dynesty.py
bajes/inf/sampler/emcee.py
bajes/inf/sampler/proposal.py
bajes/inf/sampler/ptmcmc.py
bajes/inf/sampler/ultranest.py
bajes/obs/__init__.py
bajes/obs/gw/__init__.py
bajes/obs/gw/detector.py
bajes/obs/gw/noise.py
bajes/obs/gw/strain.py
bajes/obs/gw/waveform.py
bajes/obs/gw/approx/__init__.py
bajes/obs/gw/approx/gwsurrogate.py
bajes/obs/gw/approx/lal.py
bajes/obs/gw/approx/mlgw.py
bajes/obs/gw/approx/nrpm.py
bajes/obs/gw/approx/nrpmw.py
bajes/obs/gw/approx/taylorf2.py
bajes/obs/gw/approx/teobresums.py
bajes/obs/gw/utils/__init__.py
bajes/obs/gw/utils/nrfits.py
bajes/obs/kn/__init__.py
bajes/obs/kn/filter.py
bajes/obs/kn/lightcurve.py
bajes/obs/kn/utils.py
bajes/obs/kn/approx/__init__.py
bajes/obs/kn/approx/xkn_model.py
bajes/obs/kn/approx/grossman_kbp/__init__.py
bajes/obs/kn/approx/grossman_kbp/model.py
bajes/obs/kn/approx/grossman_kbp/utils.py
bajes/obs/kn/approx/grossman_kbp/fluxfactors/ff_ray_0.dat
bajes/obs/kn/approx/grossman_kbp/fluxfactors/ff_ray_1.dat
bajes/obs/kn/approx/grossman_kbp/fluxfactors/ff_ray_10.dat
bajes/obs/kn/approx/grossman_kbp/fluxfactors/ff_ray_11.dat
bajes/obs/kn/approx/grossman_kbp/fluxfactors/ff_ray_2.dat
bajes/obs/kn/approx/grossman_kbp/fluxfactors/ff_ray_3.dat
bajes/obs/kn/approx/grossman_kbp/fluxfactors/ff_ray_4.dat
bajes/obs/kn/approx/grossman_kbp/fluxfactors/ff_ray_5.dat
bajes/obs/kn/approx/grossman_kbp/fluxfactors/ff_ray_6.dat
bajes/obs/kn/approx/grossman_kbp/fluxfactors/ff_ray_7.dat
bajes/obs/kn/approx/grossman_kbp/fluxfactors/ff_ray_8.dat
bajes/obs/kn/approx/grossman_kbp/fluxfactors/ff_ray_9.dat
bajes/obs/utils/__init__.py
bajes/obs/utils/cosmo.py
bajes/obs/utils/tov.py
bajes/pipe/__init__.py
bajes/pipe/gw_init.py
bajes/pipe/kn_init.py
bajes/pipe/log_like.py
bajes/pipe/run.py
bajes/pipe/data/gw/asd/design/CE-T2000017-v5-20km.txt
bajes-1.2.0.dist-info/LICENSE
bajes-1.2.0.dist-info/METADATA
bajes-1.2.0.dist-info/WHEEL
bajes-1.2.0.dist-info/top_level.txt
bajes-1.2.0.dist-info/RECORD
