Metadata-Version: 2.1
Name: bajes
Version: 1.2.0
Summary: Bayesian Jenaer Software
Home-page: https://github.com/matteobreschi/bajes
Author: Matteo Breschi et al.
Author-email: matteo.breschi@uni-jena.de
License: MIT
Classifier: Development Status :: 5 - Production/Stable
Classifier: License :: OSI Approved :: MIT License
Classifier: Operating System :: OS Independent
Classifier: Programming Language :: Python :: 3.7
Classifier: Programming Language :: Python :: 3.8
Classifier: Programming Language :: Python :: 3.9
Classifier: Intended Audience :: Science/Research
Classifier: Topic :: Scientific/Engineering :: Astronomy
Classifier: Topic :: Scientific/Engineering :: Physics
Requires-Python: >=3.7
License-File: LICENSE
Requires-Dist: numpy >=1.18.0
Requires-Dist: scipy >=1.4.0
Requires-Dist: astropy >=4.0.0
